{"base_url":"","routes":{"user_account":{"tokens":[["text","\/user\/account"]],"defaults":[],"requirements":[],"hosttokens":[],"methods":[],"schemes":[]},"user-edit-place":{"tokens":[["variable","\/","[^\/]++","id",true],["text","\/user\/edit\/place"]],"defaults":[],"requirements":[],"hosttokens":[],"methods":["GET","POST"],"schemes":[]},"user-add-place":{"tokens":[["text","\/user\/add\/place"]],"defaults":[],"requirements":[],"hosttokens":[],"methods":["POST"],"schemes":[]}},"prefix":"","host":"localhost","port":"","scheme":"http","locale":[]}